HowtodoinjavaJavaJiaochengChuyi/README.md
HowtodoinjavaJavaJiaochengChuyi/__init__.py
HowtodoinjavaJavaJiaochengChuyi/__main__.py
HowtodoinjavaJavaJiaochengChuyi/file.epub
HowtodoinjavaJavaJiaochengChuyi/index.html
HowtodoinjavaJavaJiaochengChuyi/css/__init__.py
HowtodoinjavaJavaJiaochengChuyi/css/annotations.css
HowtodoinjavaJavaJiaochengChuyi/css/main.css
HowtodoinjavaJavaJiaochengChuyi/css/normalize.css
HowtodoinjavaJavaJiaochengChuyi/css/popup.css
HowtodoinjavaJavaJiaochengChuyi/font/__init__.py
HowtodoinjavaJavaJiaochengChuyi/font/fontello.eot
HowtodoinjavaJavaJiaochengChuyi/font/fontello.svg
HowtodoinjavaJavaJiaochengChuyi/font/fontello.ttf
HowtodoinjavaJavaJiaochengChuyi/font/fontello.woff
HowtodoinjavaJavaJiaochengChuyi/img/__init__.py
HowtodoinjavaJavaJiaochengChuyi/img/annotator-glyph-sprite.png
HowtodoinjavaJavaJiaochengChuyi/img/annotator-icon-sprite.png
HowtodoinjavaJavaJiaochengChuyi/img/apple-touch-icon.png
HowtodoinjavaJavaJiaochengChuyi/img/cancelfullscreen.png
HowtodoinjavaJavaJiaochengChuyi/img/close.png
HowtodoinjavaJavaJiaochengChuyi/img/fullscreen.png
HowtodoinjavaJavaJiaochengChuyi/img/loader.gif
HowtodoinjavaJavaJiaochengChuyi/img/menu-icon.png
HowtodoinjavaJavaJiaochengChuyi/img/save.png
HowtodoinjavaJavaJiaochengChuyi/img/saved.png
HowtodoinjavaJavaJiaochengChuyi/img/settings-s.png
HowtodoinjavaJavaJiaochengChuyi/img/settings.png
HowtodoinjavaJavaJiaochengChuyi/img/star.png
HowtodoinjavaJavaJiaochengChuyi/js/__init__.py
HowtodoinjavaJavaJiaochengChuyi/js/epub.js
HowtodoinjavaJavaJiaochengChuyi/js/epub.min.js
HowtodoinjavaJavaJiaochengChuyi/js/epub.min.map
HowtodoinjavaJavaJiaochengChuyi/js/hooks.min.js
HowtodoinjavaJavaJiaochengChuyi/js/hooks.min.map
HowtodoinjavaJavaJiaochengChuyi/js/reader.js
HowtodoinjavaJavaJiaochengChuyi/js/reader.js.map
HowtodoinjavaJavaJiaochengChuyi/js/reader.min.js
HowtodoinjavaJavaJiaochengChuyi/js/reader.min.map
HowtodoinjavaJavaJiaochengChuyi/js/hooks/__init__.py
howtodoinjava_java_jiaocheng_chuyi-2024.3.4.0.dist-info/METADATA
howtodoinjava_java_jiaocheng_chuyi-2024.3.4.0.dist-info/WHEEL
howtodoinjava_java_jiaocheng_chuyi-2024.3.4.0.dist-info/entry_points.txt
howtodoinjava_java_jiaocheng_chuyi-2024.3.4.0.dist-info/top_level.txt
howtodoinjava_java_jiaocheng_chuyi-2024.3.4.0.dist-info/RECORD
